tiktok_signature/__init__.py
tiktok_signature/scripts.py
tiktok_signature/server.py
tiktok_signature/signature.py
tiktok_signature-1.3.dist-info/METADATA
tiktok_signature-1.3.dist-info/WHEEL
tiktok_signature-1.3.dist-info/licenses/LICENSE
tiktok_signature-1.3.dist-info/RECORD
