Metadata-Version: 2.1
Name: tiktok-signature
Version: 1.3
Summary: Some tool
Project-URL: Homepage, https://github.com/sheldygg/tiktok-signature
Author: sheldy
License-Expression: MIT
License-File: LICENSE
Classifier: Programming Language :: Python :: 3.9
Classifier: Programming Language :: Python :: 3.10
Requires-Dist: playwright
Requires-Dist: pycryptodome
Provides-Extra: server
Requires-Dist: aiohttp; extra == 'server'
